feedforward/__init__.py
feedforward/_version.py
feedforward/erasure.py
feedforward/py.typed
feedforward/run.py
feedforward/step.py
feedforward/util.py
feedforward-0.8.0.dist-info/licenses/LICENSE
feedforward-0.8.0.dist-info/METADATA
feedforward-0.8.0.dist-info/WHEEL
feedforward-0.8.0.dist-info/top_level.txt
feedforward-0.8.0.dist-info/RECORD
