Metadata-Version: 2.4
Name: feedforward
Version: 0.8.0
Summary: Simple local workflow runs
Home-page: https://github.com/advice-animal/feedforward/
Author: Tim Hatch
Author-email: tim@timhatch.com
License: MIT
Requires-Python: >=3.8
License-File: LICENSE
Provides-Extra: dev
Requires-Dist: ruff==0.11.9; extra == "dev"
Requires-Dist: checkdeps==0.9.0; extra == "dev"
Requires-Dist: mypy==1.17.0; extra == "dev"
Requires-Dist: tox==4.25.0; extra == "dev"
Provides-Extra: docs
Requires-Dist: sphinx==8.1.3; extra == "docs"
Requires-Dist: sphinx-mdinclude==0.6.2; extra == "docs"
Requires-Dist: sphinx-inline-tabs; extra == "docs"
Requires-Dist: furo; extra == "docs"
Provides-Extra: test
Requires-Dist: coverage>=6; extra == "test"
Requires-Dist: pytest; extra == "test"
Requires-Dist: pytest-cov; extra == "test"
Requires-Dist: tokenize-rt; extra == "test"
Dynamic: license-file
